ontoripple/__init__.py
ontoripple/__main__.py
ontoripple/constants.py
ontoripple/evol_kg.py
ontoripple-1.0.dist-info/LICENSE
ontoripple-1.0.dist-info/METADATA
ontoripple-1.0.dist-info/WHEEL
ontoripple-1.0.dist-info/RECORD
