Metadata-Version: 2.3
Name: ontoripple
Version: 1.0
Summary: Managing the evolution of associated knowledge graph assets
Author: Diego Conde-Herreros
Author-email: diego.conde.herreros@upm.es>, David Chaves <david.chaves@usc.es
Requires-Python: >=3.9,<4.0
Classifier: Programming Language :: Python :: 3
Classifier: Programming Language :: Python :: 3.9
Classifier: Programming Language :: Python :: 3.10
Classifier: Programming Language :: Python :: 3.11
Classifier: Programming Language :: Python :: 3.12
Classifier: Programming Language :: Python :: 3.13
Requires-Dist: coloredlogs (>=15.0.1,<16.0.0)
Requires-Dist: rdflib (>=7.1.1,<8.0.0)
Requires-Dist: ruamel-yaml (>=0.18.10,<0.19.0)
Requires-Dist: yatter (>=2.0,<3.0)
